msgpacketizer/__init__.py
msgpacketizer/localtypes.py
msgpacketizer/packer.py
msgpacketizer/py.typed
msgpacketizer/sender.py
msgpacketizer/stubs.py
msgpacketizer/subscriber.py
msgpacketizer-0.2.0.dist-info/LICENSE
msgpacketizer-0.2.0.dist-info/WHEEL
msgpacketizer-0.2.0.dist-info/METADATA
msgpacketizer-0.2.0.dist-info/RECORD
